LICENSE
MANIFEST.in
README.rst
setup.py
subwrap.py
subwrap.egg-info/PKG-INFO
subwrap.egg-info/SOURCES.txt
subwrap.egg-info/dependency_links.txt
subwrap.egg-info/not-zip-safe
subwrap.egg-info/top_level.txt