Metadata-Version: 1.1
Name: subwrap
Version: 0.1.0
Summary: subwrap - A simple wrapper for subprocess
Home-page: https://github.com/ravenac95/subwrap
Author: Reuven V. Gonzales
Author-email: reuven@tobetter.us
License: MIT
Platform: Unix
Classifier: License :: OSI Approved :: MIT License
Classifier: Intended Audience :: Developers
Classifier: Programming Language :: Python
Classifier: Operating System :: POSIX
Classifier: Programming Language :: Python
